LICENSE.txt
MANIFEST.in
README.md
setup.py
bin/pypinectrl.py
pypine/AbstractProcessor.py
pypine/Context.py
pypine/EnumAction.py
pypine/ErrorMode.py
pypine/FileTypeInfo.py
pypine/Task.py
pypine/Tasks.py
pypine/_Chain.py
pypine/_ChainNodeP.py
pypine/_INode.py
pypine/_Sequence.py
pypine/__init__.py
pypine.egg-info/PKG-INFO
pypine.egg-info/SOURCES.txt
pypine.egg-info/dependency_links.txt
pypine.egg-info/not-zip-safe
pypine.egg-info/requires.txt
pypine.egg-info/top_level.txt
pypine/do/AbstractDataObjectBase.py
pypine/do/DiskFile.py
pypine/do/InMemoryFile.py
pypine/do/URLFile.py
pypine/do/_CommonDataObjectMixin.py
pypine/do/__init__.py
pypine/processors_core/Cat.py
pypine/processors_core/ChangeFileName.py
pypine/processors_core/Delete.py
pypine/processors_core/DirScanner.py
pypine/processors_core/Echo.py
pypine/processors_core/FileWriter.py
pypine/processors_core/Noop.py
pypine/processors_core/RunTask.py
pypine/processors_core/SrcFromDict.py
pypine/processors_core/__init__.py
pypine/processors_core/core.py
pypine/pypinectrl_cli/PyPineCmd_List.py
pypine/pypinectrl_cli/PyPineCmd_Search.py
pypine/pypinectrl_cli/PyPineXModuleInfo.py
pypine/pypinectrl_cli/PyPineXSysInfo.py
pypine/pypinectrl_cli/__init__.py
pypine/utils/Color.py
pypine/utils/ObservableEvent.py
pypine/utils/RelFilePathBuilder.py
pypine/utils/TreeHelper.py
pypine/utils/__init__.py