Metadata-Version: 2.1
Name: pypine
Version: 0.2021.3.19
Summary: A Python based build and data processing framework.
Home-page: UNKNOWN
Author: Jürgen Knauth
Author-email: pubsrc@binary-overflow.de
License: Apache2
Keywords: pypine,build
Platform: UNKNOWN
Classifier: Development Status :: 3 - Alpha
Classifier: License :: OSI Approved :: Apache Software License
Classifier: Programming Language :: Python :: 3
